pyboil/__init__.py
pyboil/parser.py
pyboil/pyboil.py
pyboil/template/base/build.sh
pyboil/template/base/pyproject.toml
pyboil/template/base/setup.py
pyboil-1.0.0.dist-info/LICENSE
pyboil-1.0.0.dist-info/METADATA
pyboil-1.0.0.dist-info/WHEEL
pyboil-1.0.0.dist-info/entry_points.txt
pyboil-1.0.0.dist-info/top_level.txt
pyboil-1.0.0.dist-info/RECORD
