Metadata-Version: 2.1
Name: pyboil
Version: 1.0.0
Summary: CLI script to initialize python packages
Home-page: https://github.com/rns350/pyinit
Author: Reed Schick
Author-email: rns350@nyu.edu
Requires-Python: >=3.10
License-File: LICENSE
